[{"date":"2011-05-03","portal":"data.seattle.gov","view-id":"top-dataset-searches","count":{"gsjc-np56":2,"gis":21,"6249-gx6k":12,"yef9-cfuw":11,"nn3z-wcx3":2,"hfe7-39ey":12,"mags-97de":12,"nqji-r5pz":12,"jpzd-dj5m":10,"uyyd-8gak":3,"5ytf-wban":12,"5979-eagq":11,"8uz3-wyny":10,"7stk-8j8w":11,"ctmb-zwk6":1,"building 2009":1,"organization":2,"8mth-ajrf":2,"4rq6-vmwz":1,"a98r-tztc":12,"qq6y-w4ew":4,"j6ng-5q2r":11,"null":14344,"inqf-k78j":12,"fhf3-3dgy":29,"fthz-9fr6":1,"c2x6-dptj":4,"seattle parking map":1,"fzna-ki7a":12,"ig47-2vs9":13,"6s55-6gnf":6,"mq2z-xiq5":10,"haa3-t6c2":1,"building":1,"seattle police department incident report":2,"t9w7-6i4w":11,"2tje-83f6":12,"48zq-bcgy":11,"zq4h-ivtq":12,"vkpf-jtdi":11,"h2u8-988z":12,"park":1,"eu49-rr97":12,"47eb-r92t":1,"6pev-khgb":2,"wrgg-zpip":12,"u5e8-jif8":12,"grocery":2,"demographic ":2,"248t-t2ss":2,"k5z2-7eeb":12,"e2jt-9hzk":12,"vwis-5pa9":2,"kzjm-xkqj":7,"9wk7-cyue":1,"historical":1,"Search":3,"parks":4,"m985-ywaw":12,"m5gq-w5rr":12,"f64j-78u2":12,"qawk-qmwr":12,"tgvh-eshb":2,"nbus-pkyh":1,"vfsx-93t3":12,"6364-xtyd":12,"8pec-7ugc":1,"2fzs-85v9":2,"vawf-4au3":12,"nnxn-434b":3}}]