{"datasets-created-total":3172,"datasets-deleted-total":2036,"datasets-created-snapshot-total":1884,"datasets-deleted-snapshot-total":1045,"datasets-created-blobby-total":9,"datasets-deleted-blobby-total":9,"datasets-created-href-total":2,"charts-created-total":23984,"charts-deleted-total":23028,"maps-created-total":144,"maps-deleted-total":107,"filters-created-total":14037,"filters-deleted-total":12981,"rows-created-total":23730006,"rows-deleted-total":8232231,"page-views-total":8805157,"embeds-total":48080,"embeds":33,"rows-accessed-widget":30,"rows-loaded-widget":223,"page-views":1180,"bytes-out":409962984,"rows-accessed-download":2,"view-loaded":1300,"rows-loaded-api":25,"rows-loaded-print":8967,"rows-accessed-print":12,"rows-accessed-website":1531,"rows-loaded-download":12,"rows-accessed-api":26,"rows-loaded-rss":8677,"bytes-in":58954717,"rows-loaded-website":24762,"rows-accessed-rss":238,"disk-usage":387497984,"comments":35,"date":"2012-02-09","portal":"finances.worldbank.org"}