[{"date":"2013-06-07","portal":"bronx.lehman.cuny.edu","view-id":"gqhi-7359","count":1},{"date":"2013-06-07","portal":"bronx.lehman.cuny.edu","view-id":"9zgq-ja76","count":1},{"date":"2013-06-07","portal":"bronx.lehman.cuny.edu","view-id":"2q3n-mzjq","count":1},{"date":"2013-06-07","portal":"bronx.lehman.cuny.edu","view-id":"qbbe-vjnz","count":1},{"date":"2013-06-07","portal":"bronx.lehman.cuny.edu","view-id":"cr97-b8u3","count":2},{"date":"2013-06-07","portal":"bronx.lehman.cuny.edu","view-id":"f4wt-bja9","count":1},{"date":"2013-06-07","portal":"bronx.lehman.cuny.edu","view-id":"wich-sy2n","count":1},{"date":"2013-06-07","portal":"bronx.lehman.cuny.edu","view-id":"dnt4-z6x2","count":1},{"date":"2013-06-07","portal":"bronx.lehman.cuny.edu","view-id":"98p8-49rm","count":3},{"date":"2013-06-07","portal":"bronx.lehman.cuny.edu","view-id":"4srg-xgv7","count":1},{"date":"2013-06-07","portal":"bronx.lehman.cuny.edu","view-id":"c84z-m7di","count":1}]