[{"date":"2013-08-03","portal":"bronx.lehman.cuny.edu","view-id":"http://domainnotfound.optimum.net","count":{"/cablevassist/dnsassist/main/?domain=wwww.lehman.cuny.edu":1}},{"date":"2013-08-03","portal":"bronx.lehman.cuny.edu","view-id":"http://search.yahoo.com","count":{"/mobile/s?rewrite=72&.tsrc=apple&first=1&p=lehman+college+in+the+bronx+shows&pintl=en&pcarrier=Sprint&pmcc=310&pmnc=038&fr=onesearch":1}},{"date":"2013-08-03","portal":"bronx.lehman.cuny.edu","view-id":"http://search.lehman.edu","count":{"/search?q=after+school&btnG=Go&site=default_collection&client=default_frontend&proxystylesheet=default_frontend&output=xml_no_dtd":1,"/search?q=nursing&site=default_collection&client=default_frontend&proxystylesheet=default_frontend&output=xml_no_dtd":2}},{"date":"2013-08-03","portal":"bronx.lehman.cuny.edu","view-id":"http://www.socrata.com","count":{"/customer-spotlight/lehman-colleges-bronx-information-portal/":1}},{"date":"2013-08-03","portal":"bronx.lehman.cuny.edu","view-id":"https://www.google.com","count":{"/":1}},{"date":"2013-08-03","portal":"bronx.lehman.cuny.edu","view-id":"http://www.google.com","count":{"/search":1}},{"date":"2013-08-03","portal":"bronx.lehman.cuny.edu","view-id":"http://disqus.com","count":{"/embed/comments/?f=wiredautopia&t_i=70041%20http%3A%2F%2Fwww.wired.com%2Fautopia%2F%3Fp%3D70041&t_u=http%3A%2F%2Fwww.wired.com%2Fautopia%2F2013%2F08%2Fcrashmapper-nyc%2F&t_e=Visualizing%20New%20York%26%238217%3Bs%20Road%20Accidents%20With%20the%20Interactive%20%26%238216%3BCrashmapper%26%238217%3B&t_d=Visualizing%20New%20York's%20Road%20Accidents%20With%20the%20Interactive%20'Crashmapper'%20%7C%20Autopia%20%7C%20Wired.com&t_t=Visualizing%20New%20York%26%238217%3Bs%20Road%20Accidents%20With%20the%20Interactive%20%26%238216%3BCrashmapper%26%238217%3B&s_o=default&disqus_version=1375384862":21,"/embed/comments/?f=wiredautopia&t_i=70041%20http%3A%2F%2Fwww.wired.com%2Fautopia%2F%3Fp%3D70041&t_u=http%3A%2F%2Fwww.wired.com%2Fautopia%2F2013%2F08%2Fcrashmapper-nyc%2F&t_e=Visualizing%20New%20York%26%238217%3Bs%20Road%20Accidents%20With%20the%20Interactive%20%26%238216%3BCrashmapper%26%238217%3B&t_d=Visualizing%20New%20York%27s%20Road%20Accidents%20With%20the%20Interactive%20%27Crashmapper%27%20%7C%20Autopia%20%7C%20Wired.com&t_t=Visualizing%20New%20York%26%238217%3Bs%20Road%20Accidents%20With%20the%20Interactive%20%26%238216%3BCrashmapper%26%238217%3B&s_o=default&disqus_version=1375384862":7,"/embed/comments/?f=wiredautopia&t_i=70041%20http%3A%2F%2Fwww.wired.com%2Fautopia%2F%3Fp%3D70041&t_u=http%3A%2F%2Fwww.wired.com%2Fautopia%2F2013%2F08%2Fcrashmapper-nyc%2F&t_e=Visualizing%20New%20York%26%238217%3Bs%20Road%20Accidents%20With%20the%20Interactive%20%26%238216%3BCrashmapper%26%238217%3B&t_d=Visualizing%20New%20York%27s%20Road%20Accidents%20With%20the%20Interactive%20%27Crashmapper%27%20%7C%20Autopia%20%7C%20Wired.com&t_t=Visualizing%20New%20York%26%238217%3Bs%20Road%20Accidents%20With%20the%20Interactive%20%26%238216%3BCrashmapper%26%238217%3B&s_o=desc&disqus_version=1375384862":1}}]